lichess/__init__.py
lichess/client.py
lichess/enums.py
lichess/exceptions.py
lichess/utils.py
lichess-0.2.8.dist-info/LICENSE
lichess-0.2.8.dist-info/METADATA
lichess-0.2.8.dist-info/WHEEL
lichess-0.2.8.dist-info/top_level.txt
lichess-0.2.8.dist-info/RECORD
