Metadata-Version: 2.1
Name: lichess
Version: 0.2.8
Summary: Python wrapper for the Lichess API
Home-page: https://github.com/qe/lichess
Author: Alex Ismodes
Author-email: helloemailmerighthere@gmail.com
License: MIT
Project-URL: Documentation, https://lichess.readthedocs.io
Project-URL: Issue Tracker, https://github.com/qe/lichess/issues
Project-URL: Source Code, https://github.com/qe/lichess
Keywords: lichess chess api python wrapper
Platform: UNKNOWN
Classifier: Development Status :: 2 - Pre-Alpha
Classifier: Intended Audience :: Developers
Classifier: License :: OSI Approved :: MIT License
Classifier: Operating System :: OS Independent
Classifier: Programming Language :: Python :: 3
Classifier: Topic :: Games/Entertainment :: Board Games
Classifier: Topic :: Games/Entertainment :: Turn Based Strategy
Classifier: Topic :: Internet
Classifier: Topic :: Software Development :: Libraries
Classifier: Topic :: Software Development :: Libraries :: Python Modules
License-File: LICENSE
Requires-Dist: requests (>=2.10.0)
